state_machine_race.v
module state_machine_race (
    input clk,
    input reset,
    input wire[3:0] numero,
    input insere,
    output reg led,
    output reg[6:0] display
);


    //define os estado
    localparam sig0 = 3'b000;
    localparam sig1 = 3'b001;
    localparam sig2 = 3'b010;
    localparam sig3 = 3'b011;
    localparam sig4 = 3'b100;
    localparam sig5 = 3'b101;
    localparam sig6 = 3'b110;
    localparam sigfalha = 3'b111;
    

    //variaveis que guardam o proximo estado e o estado atual
    reg [2:0] present_state, next_state;


    reg start_led_e_next_state = 0;
    reg start_display = 0;
    reg start_present_state = 0;

    //logica de proximo estado que roda sempre que alguem insere um numero
    always @(posedge clk) begin
        if(start_led_e_next_state == 1)begin
            if(insere) begin
                if(numero < 4'b1010) begin
                    case (present_state)
                        sigfalha:
                            next_state = present_state;
                        sig6:
                            next_state = present_state;
                        sig5:
                            if (numero == 4'b1001)
                                next_state = sig6;
                            else
                                if(led == 1)
                                    led = 0;
                                else
                                    next_state = sigfalha;
                            
                        sig4:
                            if (numero == 4'b0101)
                                next_state = sig5;
                            else
                                if(led == 1)
                                    led = 0;
                                else
                                    next_state = sigfalha;
                        sig3:
                            if (numero == 4'b1001)
                                next_state = sig4;
                            else
                                if(led == 1)
                                    led = 0;
                                else
                                    next_state = sigfalha;
                        sig2:
                            if (numero == 4'b0111)
                                next_state = sig3;
                            else
                                if(led == 1)
                                    led = 0;
                                else
                                    next_state = sigfalha;
                        sig1:
                            if (numero == 4'b0011)
                                next_state = sig2;
                            else
                                if(led == 1)
                                    led = 0;
                                else
                                    next_state = sigfalha;
                        sig0:
                            if (numero == 4'b0101)
                                next_state = sig1;
                            else
                                if(led == 1)
                                    led = 0;
                                else
                                    next_state = sigfalha; 
                        default:
                            next_state = sig0;
                    endcase 
                end else begin
                    next_state = present_state;
                end
            end
            if(reset) begin
                next_state = sig0;
                led = 1;
            end
        end else begin
            led = 1;
            next_state = 3'b000;
            start_led_e_next_state = 1;
        end 
    end

    //logica de saida para os estados
    always @(posedge clk) begin

        if(start_display == 1) begin
            if(present_state == sig0 && reset == 1'b1)
                display = 7'b0000001;
            else
                if(present_state == sigfalha)
                    display = 7'b0111000;
                else if(present_state == sig6)
                    if(led == 1)
                        display = 7'b0100100;
                    else
                        display = 7'b0011000;
                else 
                    if (numero == 4'b1001)
                        display = 7'b0000100;
                    else if (numero == 4'b1000)
                        display = 7'b0000000;
                    else if (numero == 4'b0111)
                        display = 7'b0001111;
                    else if (numero == 4'b0110)
                        display = 7'b0100000;
                    else if (numero == 4'b0101)
                        display = 7'b0100100;
                    else if (numero == 4'b0100)
                        display = 7'b1001100;
                    else if (numero == 4'b0011)
                        display = 7'b0000110;
                    else if (numero == 4'b0010)
                        display = 7'b0010010;
                    else if (numero == 4'b0001)
                        display = 7'b1001111;
                    else if (numero == 4'b0000)
                        display = 7'b0000001;  
                    else
                        display = 7'b1111110;  
        end else begin
            display = 7'b0000001;
            start_display = 1;

        end
    end

    //logica de troca de estados
    always @(negedge clk) begin
        if(start_present_state == 1'b1)
            if (reset == 1'b1) begin 
                present_state = sig0;
            end else begin
                present_state = next_state;
            end
        else 
            present_state = 3'b000;
            start_present_state = 1'b1;
        

    end

endmodule

state_machine_race_tb.v
module state_machine_race_tb;
reg clk, reset, insere;
reg[3:0] numero;
wire led;
wire[6:0] display;

state_machine_race uut
(
    .clk(clk),
    .reset(reset),
    .numero(numero),
    .insere(insere),
    .led(led),
    .display(display)
);

always begin 
    #5;
    clk=~clk;
end 

initial begin
    $dumpfile("state_machine_race.vcd");
    $dumpvars(0, state_machine_race_tb);

    reset = 0; insere = 0; clk = 0;
    numero = 4'b0101; #10; insere = 1; #10; insere = 0; 
    numero = 4'b0011; #10; insere = 1; #10; insere = 0;
    numero = 4'b0111; #10; insere = 1; #10; insere = 0;
    numero = 4'b1001; #10; insere = 1; #10; insere = 0;
    numero = 4'b1100; #10; insere = 1; #10; insere = 0;
    numero = 4'b0101; #10; insere = 1; #10; insere = 0;
    numero = 4'b1001; #10; insere = 1; #10; insere = 0; #10;
    reset = 1; #10 ; reset = 0; #10;
    numero = 4'b0101; #10; insere = 1; #10; insere = 0;
    numero = 4'b0011; #10; insere = 1; #10; insere = 0;
    numero = 4'b0111; #10; insere = 1; #10; insere = 0;
    numero = 4'b1001; #10; insere = 1; #10; insere = 0;
    numero = 4'b0101; #10; insere = 1; #10; insere = 0;
    numero = 4'b0010; #10; insere = 1; #10; insere = 0;
    numero = 4'b1001; #10; insere = 1; #10; insere = 0; #10;
    reset = 1; #10 ; reset = 0; #10;
    numero = 4'b0101; #10; insere = 1; #10; insere = 0;
    numero = 4'b0011; #10; insere = 1; #10; insere = 0;
    numero = 4'b0010; #10; insere = 1; #10; insere = 0;
    numero = 4'b0001; #10; insere = 1; #10; insere = 0; #10;

    $finish;
end

endmodule

state_machine_race.vcd
$date
	Tue Jan 14 10:06:28 2025
$end
$version
	Icarus Verilog
$end
$timescale
	1s
$end
$scope module state_machine_race_tb $end
$var wire 1 ! led $end
$var wire 7 " display [6:0] $end
$var reg 1 # clk $end
$var reg 1 $ insere $end
$var reg 4 % numero [3:0] $end
$var reg 1 & reset $end
$scope module uut $end
$var wire 1 # clk $end
$var wire 1 $ insere $end
$var wire 4 ' numero [3:0] $end
$var wire 1 & reset $end
$var parameter 3 ( sig0 $end
$var parameter 3 ) sig1 $end
$var parameter 3 * sig2 $end
$var parameter 3 + sig3 $end
$var parameter 3 , sig4 $end
$var parameter 3 - sig5 $end
$var parameter 3 . sig6 $end
$var parameter 3 / sigfalha $end
$var reg 7 0 display [6:0] $end
$var reg 1 ! led $end
$var reg 3 1 next_state [2:0] $end
$var reg 3 2 present_state [2:0] $end
$var reg 1 3 start_display $end
$var reg 1 4 start_led_e_next_state $end
$var reg 1 5 start_present_state $end
$upscope $end
$upscope $end
$enddefinitions $end
$comment Show the parameter values. $end
$dumpall
b111 /
b110 .
b101 -
b100 ,
b11 +
b10 *
b1 )
b0 (
$end
#0
$dumpvars
15
04
03
b0 2
bx 1
bx 0
b101 '
0&
b101 %
0$
0#
bx "
x!
$end
#5
14
b0 1
1!
13
b1 "
b1 0
1#
#10
0#
1$
#15
b100100 "
b100100 0
b1 1
1#
#20
b1 2
0#
b11 %
b11 '
0$
#25
b110 "
b110 0
1#
#30
0#
1$
#35
b10 1
1#
#40
b10 2
0#
b111 %
b111 '
0$
#45
b1111 "
b1111 0
1#
#50
0#
1$
#55
b11 1
1#
#60
b11 2
0#
b1001 %
b1001 '
0$
#65
b100 "
b100 0
1#
#70
0#
1$
#75
b100 1
1#
#80
b100 2
0#
b1100 %
b1100 '
0$
#85
b1111110 "
b1111110 0
1#
#90
0#
1$
#95
1#
#100
0#
b101 %
b101 '
0$
#105
b100100 "
b100100 0
1#
#110
0#
1$
#115
b101 1
1#
#120
b101 2
0#
b1001 %
b1001 '
0$
#125
b100 "
b100 0
1#
#130
0#
1$
#135
b110 1
1#
#140
b110 2
0#
0$
#145
b100100 "
b100100 0
1#
#150
b0 2
0#
1&
#155
b1 "
b1 0
b0 1
1#
#160
0#
0&
#165
b100 "
b100 0
1#
#170
0#
b101 %
b101 '
#175
b100100 "
b100100 0
1#
#180
0#
1$
#185
b1 1
1#
#190
b1 2
0#
b11 %
b11 '
0$
#195
b110 "
b110 0
1#
#200
0#
1$
#205
b10 1
1#
#210
b10 2
0#
b111 %
b111 '
0$
#215
b1111 "
b1111 0
1#
#220
0#
1$
#225
b11 1
1#
#230
b11 2
0#
b1001 %
b1001 '
0$
#235
b100 "
b100 0
1#
#240
0#
1$
#245
b100 1
1#
#250
b100 2
0#
b101 %
b101 '
0$
#255
b100100 "
b100100 0
1#
#260
0#
1$
#265
b101 1
1#
#270
b101 2
0#
b10 %
b10 '
0$
#275
b10010 "
b10010 0
1#
#280
0#
1$
#285
0!
1#
#290
0#
b1001 %
b1001 '
0$
#295
b100 "
b100 0
1#
#300
0#
1$
#305
b110 1
1#
#310
b110 2
0#
0$
#315
b11000 "
b11000 0
1#
#320
b0 2
0#
1&
#325
1!
b0 1
b1 "
b1 0
1#
#330
0#
0&
#335
b100 "
b100 0
1#
#340
0#
b101 %
b101 '
#345
b100100 "
b100100 0
1#
#350
0#
1$
#355
b1 1
1#
#360
b1 2
0#
b11 %
b11 '
0$
#365
b110 "
b110 0
1#
#370
0#
1$
#375
b10 1
1#
#380
b10 2
0#
b10 %
b10 '
0$
#385
b10010 "
b10010 0
1#
#390
0#
1$
#395
0!
1#
#400
0#
b1 %
b1 '
0$
#405
b1001111 "
b1001111 0
1#
#410
0#
1$
#415
b111 1
1#
#420
b111 2
0#
0$
#425
b111000 "
b111000 0
1#
